{
	"app-id": "org.wxformbuilder.wxFormBuilder",
	"runtime": "org.freedesktop.Platform",
	"runtime-version": "21.08",
	"sdk": "org.freedesktop.Sdk",
	"command": "wxformbuilder",
	"finish-args": [
		"--socket=x11",
		"--socket=wayland",
		"--filesystem=host"
	],
	"cleanup": [ "/include" ],
	"modules": [
		{
			"name": "wxWidgets",
			"buildsystem": "autotools",
			"config-opts": [
				"--with-gtk=3",
				"--with-cxx=17",
				"--with-libiconv=/usr"
			],
			"sources": [
				{
					"type": "archive",
					"url": "https://github.com/wxWidgets/wxWidgets/releases/download/v3.1.5/wxWidgets-3.1.5.tar.bz2",
					"sha256": "d7b3666de33aa5c10ea41bb9405c40326e1aeb74ee725bb88f90f1d50270a224"
				}
			],
			"cleanup": [ "/bin/wx*", "/lib/wx" ]
		},
		{
			"name": "Boost",
			"buildsystem": "simple",
			"build-commands": [
				"./bootstrap.sh",
				"./b2 --prefix=$FLATPAK_DEST --build-dir=./build --with-headers install"
			],
			"sources": [
				{
					"type": "archive",
					"url": "https://boostorg.jfrog.io/artifactory/main/release/1.76.0/source/boost_1_76_0.tar.gz",
					"sha256": "7bd7ddceec1a1dfdcbdb3e609b60d01739c38390a5f956385a12f3122049f0ca"
				}
			],
			"cleanup": [ "/lib/cmake" ]
		},
		{
			"name": "wxFormBuilder",
			"buildsystem": "cmake",
			"config-opts": [
				"-DCMAKE_BUILD_TYPE=Release"
			],
			"sources": [
				{
					"type": "git",
					"branch": "HEAD",
					"path": "../.."
				}
			]
		}
	]
}
